Workbook

Sheet Comparables
E1: Millions | I1: Millions
A2: Competition | B2: Companies | C2: Stock price (USD) | D2: Shares outstanding (millions) | E2: Equity | F2: Total debt(long term) | G2: Cash and Cash Equvivalents | H2: Enterprise value | I2: Revenue | J2: EBIT | K2: Enterprise value /Revenue | L2: EV/EBIT | M2: EPS | N2: PE Ratio | O2: P/E =Market cap/Net Income | Q2: Burlington EBIT calculation
A3: Direct | B3: Dollar Tree | C3: 85.04 | D3: 210.8 | E3: =C3*D3 -> 17926.432 | F3: 2429.7 | G3: 666.3 | H3: =E3+F3-G3 -> 19689.832 | I3: =17578.5+9210.1-8237.5 -> 18551.1 | J3: =1462+615.1-597.7 -> 1479.4 | K3: =H3/I3 -> 1.0613835 | L3: =H3/J3 -> 13.309336 | M3: 4.83 | N3: =C3/M3 -> 17.606625
A4: Direct | B4: Ollie's Bargain Outlet Holdings | C4: 122.81 | D4: 61.806 | E4: =C4*D4 -> 7590.3949 | F4: =0.518+0.912 -> 1.43 | G4: 231.163 | H4: =E4+F4-G4 -> 7360.6619 | I4: =2271.7+1256.323-1087.193 -> 2440.83 | J4: =249.503+133.16-117.256 -> 265.407 | K4: =H4/I4 -> 3.0156389 | L4: =H4/J4 -> 27.733488 | M4: 3.23 | N4: =C4/M4 -> 38.021672 | Q4: 10-k | R4: =674.814+69.522 -> 744.336
A5: Speciatly discount competitor | B5: Five Below | C5: 148.5 | D5: 55.289 | E5: =C5*D5 -> 8210.4165 | F5: 0 | G5: 562.746 | H5: =E5+F5-G5 -> 7647.6705 | I5: =3876.527+1997.374-1641.932 -> 4231.969 | J5: =323.817+103.212-77.659 -> 349.37 | K5: =H5/I5 -> 1.8071187 | L5: =H5/J5 -> 21.889889 | M5: 4.6 | N5: =C5/M5 -> 32.282609 | O5: Fiscal Feb2025 to Jan 2026 | Q5: 10-q 2025 | R5: =260.196+33.237 -> 293.433
A6: Secondary /off price competitors | B6: Ross Stores | C6: 150.34 | D6: 325.909 | E6: =C6*D6 -> 48997.159 | F6: =499.122+1017.2 -> 1516.322 | G6: 3847.016 | H6: =E6+F6-G6 -> 46666.465 | I6: =21129.129+10514.123-10145.586 -> 21497.666 | J6: =2585.586+1244.744-1250.346 -> 2579.984 | K6: =H6/I6 -> 2.1707689 | L6: =H6/J6 -> 18.087889 | M6: 6.32 | N6: =C6/M6 -> 23.787975 | Q6: 10-q 2024 | R6: =209.306+33.231 -> 242.537
A7: Secondary /off price competitors | B7: Burlington Stores | C7: 259.9 | D7: 63.966 | E7: =C7*D7 -> 16624.763 | F7: =19.896+2019.4 -> 2039.296 | G7: 747.6 | H7: =E7+F7-G7 -> 17916.459 | I7: =10634.823+5209.092-4827.07 -> 11016.845 | J7: =R4+R5-R6 -> 795.232 | K7: =H7/I7 -> 1.6262786 | L7: =H7/J7 -> 22.529852 | M7: 7.8 | N7: =C7/M7 -> 33.320513
B9: Dollar General | C9: 103.71 | D9: 220.495 | E9: =C9*D9 -> 22867.536 | F9: =19.326+5726 -> 5745.326 | G9: 1284.6 | H9: =E9+F9-G9 -> 27328.262 | I9: =40612.308+21163.716-20124.382 -> 41651.642 | J9: =1714.074+1171.541-1096.066 -> 1789.549 | K9: =H9/I9 -> 0.65611489 | L9: =H9/J9 -> 15.271033 | M9: 7.55 | N9: =C9/M9 -> 13.736424
A11: Computations for 2025: | B11: Revenue multiple
A12: Enterprise value/revenue | D12: Implied EV | G12: Implied Equity | J12: Implied stock price
A13: Min | B13: =MIN(K3:K7) -> 1.0613835 | D13: Min | E13: =B13*$I$9 -> 44208.367 | G13: Min | H13: =E13+$G$9-$F$9 -> 39747.641 | J13: Min | K13: =H13/$D$9 -> 180.2655
A14: Average | B14: =AVERAGE(K3:K7) -> 1.9362377 | D14: Average | E14: =B14*$I$9 -> 80647.481 | G14: Average | H14: =E14+$G$9-$F$9 -> 76186.755 | J14: Average | K14: =H14/$D$9 -> 345.526
A15: Max | B15: =MAX(K3:K7) -> 3.0156389 | D15: Max | E15: =B15*$I$9 -> 125606.31 | G15: Max | H15: =E15+$G$9-$F$9 -> 121145.59 | J15: Max | K15: =H15/$D$9 -> 549.42554
A17: EBIT multiple
A18: EV/EBIT | D18: Implied EV | G18: Implied Equity | J18: Implied stock price
A19: Min | B19: =MIN(L3:L7) -> 13.309336 | D19: Min | E19: =B19*$J$9 -> 23817.709 | G19: Min | H19: =E19+$G$9-$F$9 -> 19356.983 | J19: Min | K19: =H19/$D$9 -> 87.788763
A20: Average | B20: =AVERAGE(L3:L7) -> 20.710091 | D20: Average | E20: =B20*$J$9 -> 37061.723 | G20: Average | H20: =E20+$G$9-$F$9 -> 32600.997 | J20: Average | K20: =H20/$D$9 -> 147.85368
A21: Max | B21: =MAX(L3:L7) -> 27.733488 | D21: Max | E21: =B21*$J$9 -> 49630.436 | G21: Max | H21: =E21+$G$9-$F$9 -> 45169.71 | J21: Max | K21: =H21/$D$9 -> 204.85594
A24: Sales forecast to be assumed for 2026 | B24: =DCF_baseline!G4 -> 42033.739
A27: Computations for 2026: | B27: Revenue Multiple
A28: Enterprise value/revenue | D28: Implied EV | G28: Implied Equity | J28: Implied stock price
A29: Min | B29: =MIN(K3:K7) -> 1.0613835 | D29: Min | E29: =B29*$B$24 -> 44613.918 | G29: Min | H29: =E29-$F$9+$G$9 -> 40153.192 | J29: Min | K29: =H29/$D$9 -> 182.10477
A30: Average | B30: =AVERAGE(K3:K7) -> 1.9362377 | D30: Average | E30: =B30*$B$24 -> 81387.311 | G30: Average | H30: =E30-$F$9+$G$9 -> 76926.585 | J30: Average | K30: =H30/$D$9 -> 348.88131
A31: Max | B31: =MAX(K3:K7) -> 3.0156389 | D31: Max | E31: =B31*$B$24 -> 126758.58 | G31: Max | H31: =E31-$F$9+$G$9 -> 122297.85 | J31: Max | K31: =H31/$D$9 -> 554.65136
A33: EBIT multiple
A34: EV/EBIT | D34: Implied EV | G34: Implied Equity | J34: Implied stock price
A35: Min | B35: =MIN(L3:L7) -> 13.309336 | D35: Min | E35: =B35*$J$9 -> 23817.709 | G35: Min | H35: =E35+$G$9-$F$9 -> 19356.983 | J35: Min | K35: =H35/$D$9 -> 87.788763
A36: Average | B36: =AVERAGE(L3:L7) -> 20.710091 | D36: Average | E36: =B36*$J$9 -> 37061.723 | G36: Average | H36: =E36+$G$9-$F$9 -> 32600.997 | J36: Average | K36: =H36/$D$9 -> 147.85368
A37: Max | B37: =MAX(L3:L7) -> 27.733488 | D37: Max | E37: =B37*$J$9 -> 49630.436 | G37: Max | H37: =E37+$G$9-$F$9 -> 45169.71 | J37: Max | K37: =H37/$D$9 -> 204.85594

Sheet Precedent Analysis 
B1: Precedent Analysis
B2: Acquiring Company | C2: Target Company | D2: Acquisition Date | E2: Acquiring Price | F2: No.of Shares(in millions) | G2: Equity(in millions) | H2: Debt | I2: Cash | J2: EV | K2: Revenue | L2: EBIT | M2: EV/Revenue | N2: EV/ EBIT
B3: Apollo Global Management | C3: The Michaels Companies | D3: 44276 | E3: 22 | F3: 146.803 | G3: =F3*E3 -> 3229.666 | H3: =16.7+2480.953 -> 2497.653 | I3: 1194.389 | J3: =G3+H3-I3 -> 4532.93 | K3: 5271.112 | L3: 533.54 | M3: =J3/K3 -> 0.85995706 | N3: =J3/L3 -> 8.4959516 | O3: Fiscal year
B4: LVMH | C4: Tiffany&Co | D4: 43794 | E4: 135 | F4: 123.5 | G4: =F4*E4 -> 16672.5 | H4: 884.1 | I4: 874.7 | J4: =G4+H4-I4 -> 16681.9 | K4: =4424+2310.8-3066.1 -> 3668.7 | L4: =732.6+119.2-463.6 -> 388.2 | M4: =J4/K4 -> 4.5470875 | N4: =J4/L4 -> 42.972437
B5: Sycamore partner | C5: Staples | D5: 42914 | E5: 10.25 | F5: 652.52 | G5: =F5*E5 -> 6688.33 | H5: 529 | I5: 1137 | J5: =G5+H5-I5 -> 6080.33 | K5: 18247 | L5: 888 | M5: =J5/K5 -> 0.33322354 | N5: =J5/L5 -> 6.8472185 | O5: Fiscal year
B6: BC Partners | C6: Pet smart | D6: 42074 | E6: 83 | F6: 109.611 | G6: =F6*E6 -> 9097.713 | H6: 0 | I6: 285.622 | J6: =G6+H6-I6 -> 8812.091 | K6: 6916.627 | L6: 693.318 | M6: =J6/K6 -> 1.2740446 | N6: =J6/L6 -> 12.710028 | O6: 52 weeks data provided
E7: stock price
B8: Dollar General | E8: 103.71 | F8: 220.495 | G8: =E8*F8 -> 22867.536 | H8: =19.326+5726 -> 5745.326 | I8: 1284.6 | J8: =G8+H8-I8 -> 27328.262 | K8: =40612.308+21163.716-20124.382 -> 41651.642 | L8: =1714.074+1171.541-1096.066 -> 1789.549 | M8: =J8/K8 -> 0.65611489 | N8: =J8/L8 -> 15.271033
B10: Comparables | C10: EV/Rev | D10: Ev/EBIT | E10: Implied EV | F10: Implied Equity | G10: Implied stock price
B11: Min | C11: =MIN(M3:M6) -> 0.33322354 | D11: =MIN(N3:N6) -> 6.8472185 | E11: =C11*$K$8 -> 13879.308 | F11: =E11+$I$8-$H$8 -> 9418.5817 | G11: =F11/$F$8 -> 42.715625
B12: Avg | C12: =AVERAGE(M3:M6) -> 1.7535782 | D12: =AVERAGE(N3:N6) -> 17.756409 | E12: =C12*$K$8 -> 73039.41 | F12: =E12+$I$8-$H$8 -> 68578.684 | G12: =F12/$F$8 -> 311.02149
B13: Max | C13: =MAX(M3:M6) -> 4.5470875 | D13: =MAX(N3:N6) -> 42.972437 | E13: =C13*$K$8 -> 189393.66 | F13: =E13+$I$8-$H$8 -> 184932.94 | G13: =F13/$F$8 -> 838.71714

Sheet DCF_baseline
G2: FORECAST
B3: 2021 | C3: 2022 | D3: 2023 | E3: 2024 | F3: 2025 | G3: 2026 | H3: 2027 | I3: 2028 | J3: 2029 | K3: 2030 | L3: Beyond 2031
A4: Sales | B4: 33746.839 | C4: 34220.449 | D4: 37844.863 | E4: 38691.609 | F4: 40612.308 | G4: =(1+G5)*F4 -> 42033.739 | H4: =(1+H5)*G4 -> 43462.886 | I4: =(1+I5)*H4 -> 44853.698 | J4: =(1+J5)*I4 -> 46199.309 | K4: =(1+K5)*J4 -> 47492.89
A5: % Growth | C5: =(C4-B4)/B4 -> 0.014034203 | D5: =(D4-C4)/C4 -> 0.10591369 | E5: =(E4-D4)/D4 -> 0.022374133 | F5: =(F4-E4)/E4 -> 0.049641228 | G5: 0.035 | H5: 0.034 | I5: 0.032 | J5: 0.03 | K5: 0.028 | L5: 0.025
A7: EBITDA | B7: =B10+B14 -> 4129.002 | C7: =C10+C14 -> 3861.991 | D7: =D10+D14 -> 4053.179 | E7: =E10+E14 -> 3295.093 | F7: =F10+F14 -> 2685.777 | G7: =G8*G4 -> 4149.5995 | H7: =H8*H4 -> 4290.6858 | I7: =I8*I4 -> 4427.9878 | J7: =J8*J4 -> 4560.8274 | K7: =K8*K4 -> 4688.5306
A8: % Sales | B8: =B7/B4 -> 0.12235226 | C8: =C7/C4 -> 0.11285623 | D8: =D7/D4 -> 0.10709985 | E8: =E7/E4 -> 0.085162987 | F8: =F7/F4 -> 0.066132095 | G8: =AVERAGE(B8:F8) -> 0.098720684 | H8: =G8 -> 0.098720684 | I8: =H8 -> 0.098720684 | J8: =I8 -> 0.098720684 | K8: =J8 -> 0.098720684
A10: EBIT | B10: 3554.765 | C10: 3220.675 | D10: 3328.302 | E10: 2446.3 | F10: 1714.074 | G10: =G11*G4 -> 3783.0365 | H10: =H11*H4 -> 3911.6597 | I10: =I11*I4 -> 4036.8328 | J10: =J11*J4 -> 4157.9378 | K10: =K11*K4 -> 4274.3601
A11: % Sales | B11: =B10/B4 -> 0.10533624 | C11: =C10/C4 -> 0.09411551 | D11: =D10/D4 -> 0.087945939 | E11: =E10/E4 -> 0.063225595 | F11: =F10/F4 -> 0.042205777 | G11: 0.09 | H11: 0.09 | I11: 0.09 | J11: 0.09 | K11: 0.09
A13: Assets | B13: 25862.624 | C13: 26327.371 | D13: 29083.367 | E13: 30795.591 | F13: 31132.733
A14: Depreciation & Amortization | B14: 574.237 | C14: 641.316 | D14: 724.877 | E14: 848.793 | F14: 971.703 | G14: =G17*G4 -> 847.18467 | H14: =H17*H4 -> 875.98895 | I14: =I17*I4 -> 904.02059 | J14: =J17*J4 -> 931.14121 | K14: =K17*K4 -> 957.21317
A15: CAPX | B15: 1027.963 | C15: 1070.46 | D15: 1560.582 | E15: 1700.222 | F15: 1309.888 | G15: =G18*G4 -> 1506.279 | H15: =H18*H4 -> 1557.4925 | I15: =I18*I4 -> 1607.3322 | J15: =J18*J4 -> 1655.5522 | K15: =K18*K4 -> 1701.9077
A17: Dep and Amortr as % sales | B17: =B14/B4 -> 0.017016023 | C17: =C14/C4 -> 0.018740724 | D17: =D14/D4 -> 0.019153907 | E17: =E14/E4 -> 0.021937392 | F17: =F14/F4 -> 0.023926318 | G17: =AVERAGE(B17:F17) -> 0.020154873 | H17: =G17 -> 0.020154873 | I17: =H17 -> 0.020154873 | J17: =I17 -> 0.020154873 | K17: =J17 -> 0.020154873
A18: Capex as %sales | B18: =B15/B4 -> 0.030461016 | C18: =C15/C4 -> 0.031281296 | D18: =D15/D4 -> 0.041236297 | E18: =E15/E4 -> 0.043942913 | F18: =F15/F4 -> 0.032253474 | G18: =AVERAGE(B18:F18) -> 0.035834999 | H18: =G18 -> 0.035834999 | I18: =H18 -> 0.035834999 | J18: =I18 -> 0.035834999 | K18: =J18 -> 0.035834999
A20: NOWC | B20: =(6914.219-1376.577)-5710.783 -> -173.141 | C20: =(6303.843)-5979.357 -> 324.486 | D20: =(7581.009-381.576)-(5887.768-1288.939) -> 2600.604 | E20: =(8010.724-537.283)-(6725.701-768.645) -> 1516.385 | F20: =(8163.925-932.576)-(6868.702-519.463) -> 882.11 | G20: =G21*G4 -> 840.67478 | H20: =H21*H4 -> 869.25772 | I20: =I21*I4 -> 897.07396 | J20: =J21*J4 -> 923.98618 | K20: =K21*K4 -> 949.8578
A21: NOWC as % of sales | B21: =B20/B4 -> -0.0051305842 | C21: =C20/C4 -> 0.0094822251 | D21: =D20/D4 -> 0.06871749 | E21: =E20/E4 -> 0.039191573 | F21: =F20/F4 -> 0.021720263 | G21: 0.02 | H21: 0.02 | I21: 0.02 | J21: 0.02 | K21: 0.02
A22: changes in NOWC | G22: =G20-F20 -> -41.435224 | H22: =H20-G20 -> 28.582942 | I22: =I20-H20 -> 27.816247 | J22: =J20-I20 -> 26.912219 | K22: =K20-J20 -> 25.871613
M23: Tax rate | N23: 0.22
A24: FCF | G24: =G10*(1-N23)+G14-(G15+G21) -> 2291.6541 | H24: =H10*(1-O23)+H14-(H15+H21) -> 3230.1362 | I24: =I10*(1-P23)+I14-(I15+I21) -> 3333.5012 | J24: =J10*(1-Q23)+J14-(J15+J21) -> 3433.5068 | K24: =K10*(1-R23)+K14-(K15+K21) -> 3529.6456 | O24: FCF=EBIT*(1-t)+dep-(capex+chnages in nowc)
A27: Calculation of WACC | D27: Calculation of CAPM | G27: Cash | H27: =Comparables!G9 -> 1284.6
A28: Wd | B28: =B34/B36 -> 0.21433666 | D28: Rf+beta*(MRP) | G28: Debt | H28: =B34 -> 6238.488
A29: We | B29: =B35/B36 -> 0.78566334 | D29: Rf | E29: 0.0414 | G29: Total Equity | H29: =E40+H27-H28 -> 18921.334 | L29: Sensitivity analysis
A30: rd (BBB rating) | B30: 5.01 | D30: beta | E30: 0.31 | G30: # shares | H30: =Comparables!D9 -> 220.495 | L30: =H31 -> 85.812984 | M30: 0.035 | N30: 0.04 | O30: 0.045 | P30: 0.05 | Q30: 0.055 | R30: 0.06
A31: re | B31: 5.69 | D31: MRP | E31: 0.05 | F31: assumed | G31: Stock Price | H31: =H29/H30 -> 85.812984 | L31: 0.05 | M31: 87.396411 | N31: 87.396411 | O31: 87.396411 | P31: 87.396411 | Q31: 87.396411 | R31: 87.396411
A32: rd(1-t) | B32: =B30*(1-0.22) -> 3.9078 | D32: CAPM | E32: =E29+E30*E31 -> 0.0569 | L32: 0.055 | M32: 84.68737 | N32: 84.68737 | O32: 84.68737 | P32: 84.68737 | Q32: 84.68737 | R32: 84.68737
L33: 0.06 | M33: 82.076241 | N33: 82.076241 | O33: 82.076241 | P33: 82.076241 | Q33: 82.076241 | R33: 82.076241
A34: Book value of debt | B34: =519.463+5719.025 -> 6238.488 | D34: Constant g | E34: 0.03 | L34: 0.065 | M34: 79.558686 | N34: 79.558686 | O34: 79.558686 | P34: 79.558686 | Q34: 79.558686 | R34: 79.558686
A35: Market value of equity | B35: =Comparables!E9 -> 22867.536 | D35: WACC | E35: 0.0529 | L35: 0.07 | M35: 77.130587 | N35: 77.130587 | O35: 77.130587 | P35: 77.130587 | Q35: 77.130587 | R35: 77.130587
A36: Total | B36: =B34+B35 -> 29106.024 | H36: Stock Price | L36: 0.075 | M36: 74.788036 | N36: 74.788036 | O36: 74.788036 | P36: 74.788036 | Q36: 74.788036 | R36: 74.788036
D37: Terminal value | E37: =K24*(1+E34)/(E35-E34) -> 158756.99 | G37: Baseline | H37: 85.81 | L37: 0.08 | M37: 72.527322 | N37: 72.527322 | O37: 72.527322 | P37: 72.527322 | Q37: 72.527322 | R37: 72.527322
A38: WACC | B38: =(B28*B32)+(B29*B31) -> 5.3080092 | D38: PV of FCFs | E38: =NPV(E35,G24:K24) -> 13467.558 | G38: Downside | H38: =DCF_downside!H31 -> 84.595324
D39: PV of TV | E39: =E38/(1+E35)^5 -> 10407.663 | G39: Upside | H39: =DCF_upside!H31 -> 86.886466
D40: Enterprise value | E40: =E38+E39 -> 23875.222

Sheet DCF_downside
G2: FORECAST
B3: 2021 | C3: 2022 | D3: 2023 | E3: 2024 | F3: 2025 | G3: 2026 | H3: 2027 | I3: 2028 | J3: 2029 | K3: 2030 | L3: Beyond 2031
A4: Sales | B4: 33746.839 | C4: 34220.449 | D4: 37844.863 | E4: 38691.609 | F4: 40612.308 | G4: =(1+G5)*F4 -> 41911.902 | H4: =(1+H5)*G4 -> 43211.171 | I4: =(1+I5)*H4 -> 44421.084 | J4: =(1+J5)*I4 -> 45531.611 | K4: =(1+K5)*J4 -> 46442.243
A5: % Growth | C5: =(C4-B4)/B4 -> 0.014034203 | D5: =(D4-C4)/C4 -> 0.10591369 | E5: =(E4-D4)/D4 -> 0.022374133 | F5: =(F4-E4)/E4 -> 0.049641228 | G5: 0.032 | H5: 0.031 | I5: 0.028 | J5: 0.025 | K5: 0.02 | L5: 0.02
A7: EBITDA | B7: =B10+B14 -> 4129.002 | C7: =C10+C14 -> 3861.991 | D7: =D10+D14 -> 4053.179 | E7: =E10+E14 -> 3295.093 | F7: =F10+F14 -> 2685.777 | G7: =G8*G4 -> 4137.5716 | H7: =H8*H4 -> 4265.8364 | I7: =I8*I4 -> 4385.2798 | J7: =J8*J4 -> 4494.9118 | K7: =K8*K4 -> 4584.81
A8: % Sales | B8: =B7/B4 -> 0.12235226 | C8: =C7/C4 -> 0.11285623 | D8: =D7/D4 -> 0.10709985 | E8: =E7/E4 -> 0.085162987 | F8: =F7/F4 -> 0.066132095 | G8: =AVERAGE(B8:F8) -> 0.098720684 | H8: =G8 -> 0.098720684 | I8: =H8 -> 0.098720684 | J8: =I8 -> 0.098720684 | K8: =J8 -> 0.098720684
A10: EBIT | B10: 3554.765 | C10: 3220.675 | D10: 3328.302 | E10: 2446.3 | F10: 1714.074 | G10: =G11*G4 -> 3772.0712 | H10: =H11*H4 -> 3889.0054 | I10: =I11*I4 -> 3997.8975 | J10: =J11*J4 -> 4097.845 | K10: =K11*K4 -> 4179.8019
A11: % Sales | B11: =B10/B4 -> 0.10533624 | C11: =C10/C4 -> 0.09411551 | D11: =D10/D4 -> 0.087945939 | E11: =E10/E4 -> 0.063225595 | F11: =F10/F4 -> 0.042205777 | G11: 0.09 | H11: 0.09 | I11: 0.09 | J11: 0.09 | K11: 0.09
A13: Assets | B13: 25862.624 | C13: 26327.371 | D13: 29083.367 | E13: 30795.591 | F13: 31132.733
A14: Depreciation & Amortization | B14: 574.237 | C14: 641.316 | D14: 724.877 | E14: 848.793 | F14: 971.703 | G14: =G17*G4 -> 844.72906 | H14: =H17*H4 -> 870.91566 | I14: =I17*I4 -> 895.3013 | J14: =J17*J4 -> 917.68383 | K14: =K17*K4 -> 936.03751
A15: CAPX | B15: 1027.963 | C15: 1070.46 | D15: 1560.582 | E15: 1700.222 | F15: 1309.888 | G15: =G18*G4 -> 1501.913 | H15: =H18*H4 -> 1548.4723 | I15: =I18*I4 -> 1591.8295 | J15: =J18*J4 -> 1631.6252 | K15: =K18*K4 -> 1664.2577
A17: Dep and Amortr as % sales | B17: =B14/B4 -> 0.017016023 | C17: =C14/C4 -> 0.018740724 | D17: =D14/D4 -> 0.019153907 | E17: =E14/E4 -> 0.021937392 | F17: =F14/F4 -> 0.023926318 | G17: =AVERAGE(B17:F17) -> 0.020154873 | H17: =G17 -> 0.020154873 | I17: =H17 -> 0.020154873 | J17: =I17 -> 0.020154873 | K17: =J17 -> 0.020154873
A18: Capex as %sales | B18: =B15/B4 -> 0.030461016 | C18: =C15/C4 -> 0.031281296 | D18: =D15/D4 -> 0.041236297 | E18: =E15/E4 -> 0.043942913 | F18: =F15/F4 -> 0.032253474 | G18: =AVERAGE(B18:F18) -> 0.035834999 | H18: =G18 -> 0.035834999 | I18: =H18 -> 0.035834999 | J18: =I18 -> 0.035834999 | K18: =J18 -> 0.035834999
A20: NOWC | B20: =(6914.219-1376.577)-5710.783 -> -173.141 | C20: =(6303.843)-5979.357 -> 324.486 | D20: =(7581.009-381.576)-(5887.768-1288.939) -> 2600.604 | E20: =(8010.724-537.283)-(6725.701-768.645) -> 1516.385 | F20: =(8163.925-932.576)-(6868.702-519.463) -> 882.11 | G20: =G21*G4 -> 838.23804 | H20: =H21*H4 -> 864.22342 | I20: =I21*I4 -> 888.42167 | J20: =J21*J4 -> 910.63221 | K20: =K21*K4 -> 928.84486
A21: NOWC as % of sales | B21: =B20/B4 -> -0.0051305842 | C21: =C20/C4 -> 0.0094822251 | D21: =D20/D4 -> 0.06871749 | E21: =E20/E4 -> 0.039191573 | F21: =F20/F4 -> 0.021720263 | G21: 0.02 | H21: 0.02 | I21: 0.02 | J21: 0.02 | K21: 0.02
A22: changes in NOWC | G22: =G20-F20 -> -43.871963 | H22: =H20-G20 -> 25.985379 | I22: =I20-H20 -> 24.198256 | J22: =J20-I20 -> 22.210542 | K22: =K20-J20 -> 18.212644
M23: Tax rate | N23: 0.22
A24: FCF | G24: =G10*(1-N23)+G14-(G15+G21) -> 2285.0116 | H24: =H10*(1-O23)+H14-(H15+H21) -> 3211.4288 | I24: =I10*(1-P23)+I14-(I15+I21) -> 3301.3493 | J24: =J10*(1-Q23)+J14-(J15+J21) -> 3383.8836 | K24: =K10*(1-R23)+K14-(K15+K21) -> 3451.5616 | O24: FCF=EBIT*(1-t)+dep-(capex+chnages in nowc)
A27: Calculation of WACC | D27: Calculation of CAPM | G27: Cash | H27: =Comparables!G9 -> 1284.6
A28: Wd | B28: =B34/B36 -> 0.21433666 | D28: Rf+beta*(MRP) | G28: Debt | H28: =B34 -> 6238.488
A29: We | B29: =B35/B36 -> 0.78566334 | D29: Rf | E29: 0.0414 | G29: Total Equity | H29: =E40+H27-H28 -> 18652.846
A30: rd (BBB rating) | B30: 5.01 | D30: beta | E30: 0.31 | G30: # shares | H30: =Comparables!D9 -> 220.495
A31: re | B31: 5.69 | D31: MRP | E31: 0.05 | F31: assumed | G31: Stock Price | H31: =H29/H30 -> 84.595324
A32: rd(1-t) | B32: =B30*(1-0.22) -> 3.9078 | D32: CAPM | E32: =E29+E30*E31 -> 0.0569
J33: =H31 -> 84.595324 | K33: 0.035 | L33: 0.04 | M33: 0.045 | N33: 0.05 | O33: 0.055 | P33: 0.06
A34: Book value of debt | B34: =519.463+5719.025 -> 6238.488 | D34: Constant g | E34: 0.02 | J34: 0.06 | K34: 80.906886 | L34: 80.906886 | M34: 80.906886 | N34: 80.906886 | O34: 80.906886 | P34: 80.906886
A35: Market value of equity | B35: =Comparables!E9 -> 22867.536 | D35: WACC | E35: 0.0529 | J35: 0.065 | K35: 78.42178 | L35: 78.42178 | M35: 78.42178 | N35: 78.42178 | O35: 78.42178 | P35: 78.42178
A36: Total | B36: =B34+B35 -> 29106.024 | J36: 0.07 | K36: 76.024902 | L36: 76.024902 | M36: 76.024902 | N36: 76.024902 | O36: 76.024902 | P36: 76.024902
D37: Terminal value | E37: =K24*(1+E34)/(E35-E34) -> 107008.9 | J37: 0.075 | K37: 73.7124 | L37: 73.7124 | M37: 73.7124 | N37: 73.7124 | O37: 73.7124 | P37: 73.7124
A38: WACC | B38: =(B28*B32)+(B29*B31) -> 5.3080092 | D38: PV of FCFs | E38: =NPV(E35,G24:K24) -> 13316.109 | J38: 0.08 | K38: 71.480615 | L38: 71.480615 | M38: 71.480615 | N38: 71.480615 | O38: 71.480615 | P38: 71.480615
D39: PV of TV | E39: =E38/(1+E35)^5 -> 10290.624 | J39: 0.085 | K39: 69.32607 | L39: 69.32607 | M39: 69.32607 | N39: 69.32607 | O39: 69.32607 | P39: 69.32607
D40: Enterprise value | E40: =E38+E39 -> 23606.734

Sheet DCF_upside
G2: FORECAST
B3: 2021 | C3: 2022 | D3: 2023 | E3: 2024 | F3: 2025 | G3: 2026 | H3: 2027 | I3: 2028 | J3: 2029 | K3: 2030 | L3: Beyond 2031
A4: Sales | B4: 33746.839 | C4: 34220.449 | D4: 37844.863 | E4: 38691.609 | F4: 40612.308 | G4: =(1+G5)*F4 -> 42236.8 | H4: =(1+H5)*G4 -> 43841.799 | I4: =(1+I5)*H4 -> 45376.262 | J4: =(1+J5)*I4 -> 46737.55 | K4: =(1+K5)*J4 -> 48046.201
A5: % Growth | C5: =(C4-B4)/B4 -> 0.014034203 | D5: =(D4-C4)/C4 -> 0.10591369 | E5: =(E4-D4)/D4 -> 0.022374133 | F5: =(F4-E4)/E4 -> 0.049641228 | G5: 0.04 | H5: 0.038 | I5: 0.035 | J5: 0.03 | K5: 0.028 | L5: 0.025
A7: EBITDA | B7: =B10+B14 -> 4129.002 | C7: =C10+C14 -> 3861.991 | D7: =D10+D14 -> 4053.179 | E7: =E10+E14 -> 3295.093 | F7: =F10+F14 -> 2685.777 | G7: =G8*G4 -> 4169.6458 | H7: =H8*H4 -> 4328.0924 | I7: =I8*I4 -> 4479.5756 | J7: =J8*J4 -> 4613.9629 | K7: =K8*K4 -> 4743.1538
A8: % Sales | B8: =B7/B4 -> 0.12235226 | C8: =C7/C4 -> 0.11285623 | D8: =D7/D4 -> 0.10709985 | E8: =E7/E4 -> 0.085162987 | F8: =F7/F4 -> 0.066132095 | G8: =AVERAGE(B8:F8) -> 0.098720684 | H8: =G8 -> 0.098720684 | I8: =H8 -> 0.098720684 | J8: =I8 -> 0.098720684 | K8: =J8 -> 0.098720684
A10: EBIT | B10: 3554.765 | C10: 3220.675 | D10: 3328.302 | E10: 2446.3 | F10: 1714.074 | G10: =G11*G4 -> 3801.312 | H10: =H11*H4 -> 3945.7619 | I10: =I11*I4 -> 4083.8636 | J10: =J11*J4 -> 4206.3795 | K10: =K11*K4 -> 4324.1581
A11: % Sales | B11: =B10/B4 -> 0.10533624 | C11: =C10/C4 -> 0.09411551 | D11: =D10/D4 -> 0.087945939 | E11: =E10/E4 -> 0.063225595 | F11: =F10/F4 -> 0.042205777 | G11: 0.09 | H11: 0.09 | I11: 0.09 | J11: 0.09 | K11: 0.09
A13: Assets | B13: 25862.624 | C13: 26327.371 | D13: 29083.367 | E13: 30795.591 | F13: 31132.733
A14: Depreciation & Amortization | B14: 574.237 | C14: 641.316 | D14: 724.877 | E14: 848.793 | F14: 971.703 | G14: =G17*G4 -> 851.27735 | H14: =H17*H4 -> 883.62589 | I14: =I17*I4 -> 914.55279 | J14: =J17*J4 -> 941.98938 | K14: =K17*K4 -> 968.36508
A15: CAPX | B15: 1027.963 | C15: 1070.46 | D15: 1560.582 | E15: 1700.222 | F15: 1309.888 | G15: =G18*G4 -> 1513.5557 | H15: =H18*H4 -> 1571.0708 | I15: =I18*I4 -> 1626.0583 | J15: =J18*J4 -> 1674.84 | K15: =K18*K4 -> 1721.7356
A17: Dep and Amortr as % sales | B17: =B14/B4 -> 0.017016023 | C17: =C14/C4 -> 0.018740724 | D17: =D14/D4 -> 0.019153907 | E17: =E14/E4 -> 0.021937392 | F17: =F14/F4 -> 0.023926318 | G17: =AVERAGE(B17:F17) -> 0.020154873 | H17: =G17 -> 0.020154873 | I17: =H17 -> 0.020154873 | J17: =I17 -> 0.020154873 | K17: =J17 -> 0.020154873
A18: Capex as %sales | B18: =B15/B4 -> 0.030461016 | C18: =C15/C4 -> 0.031281296 | D18: =D15/D4 -> 0.041236297 | E18: =E15/E4 -> 0.043942913 | F18: =F15/F4 -> 0.032253474 | G18: =AVERAGE(B18:F18) -> 0.035834999 | H18: =G18 -> 0.035834999 | I18: =H18 -> 0.035834999 | J18: =I18 -> 0.035834999 | K18: =J18 -> 0.035834999
A20: NOWC | B20: =(6914.219-1376.577)-5710.783 -> -173.141 | C20: =(6303.843)-5979.357 -> 324.486 | D20: =(7581.009-381.576)-(5887.768-1288.939) -> 2600.604 | E20: =(8010.724-537.283)-(6725.701-768.645) -> 1516.385 | F20: =(8163.925-932.576)-(6868.702-519.463) -> 882.11 | G20: =G21*G4 -> 844.73601 | H20: =H21*H4 -> 876.83597 | I20: =I21*I4 -> 907.52523 | J20: =J21*J4 -> 934.75099 | K20: =K21*K4 -> 960.92402
A21: NOWC as % of sales | B21: =B20/B4 -> -0.0051305842 | C21: =C20/C4 -> 0.0094822251 | D21: =D20/D4 -> 0.06871749 | E21: =E20/E4 -> 0.039191573 | F21: =F20/F4 -> 0.021720263 | G21: 0.02 | H21: 0.02 | I21: 0.02 | J21: 0.02 | K21: 0.02
A22: changes in NOWC | G22: =G20-F20 -> -37.373994 | H22: =H20-G20 -> 32.099968 | I22: =I20-H20 -> 30.689259 | J22: =J20-I20 -> 27.225757 | K22: =K20-J20 -> 26.173028
M23: Tax rate | N23: 0.22
A24: FCF | G24: =G10*(1-N23)+G14-(G15+G21) -> 2302.725 | H24: =H10*(1-O23)+H14-(H15+H21) -> 3258.297 | I24: =I10*(1-P23)+I14-(I15+I21) -> 3372.3381 | J24: =J10*(1-Q23)+J14-(J15+J21) -> 3473.5088 | K24: =K10*(1-R23)+K14-(K15+K21) -> 3570.7676 | O24: FCF=EBIT*(1-t)+dep-(capex+chnages in nowc)
A27: Calculation of WACC | D27: Calculation of CAPM | G27: Cash | H27: =Comparables!G9 -> 1284.6
A28: Wd | B28: =B34/B36 -> 0.21433666 | D28: Rf+beta*(MRP) | G28: Debt | H28: =B34 -> 6238.488
A29: We | B29: =B35/B36 -> 0.78566334 | D29: Rf | E29: 0.0414 | G29: Total Equity | H29: =E40+H27-H28 -> 19158.031
A30: rd (BBB rating) | B30: 5.01 | D30: beta | E30: 0.31 | G30: # shares | H30: =Comparables!D9 -> 220.495
A31: re | B31: 5.69 | D31: MRP | E31: 0.05 | F31: assumed | G31: Stock Price | H31: =H29/H30 -> 86.886466
A32: rd(1-t) | B32: =B30*(1-0.22) -> 3.9078 | D32: CAPM | E32: =E29+E30*E31 -> 0.0569
A34: Book value of debt | B34: =519.463+5719.025 -> 6238.488 | D34: Constant g | E34: 0.04
A35: Market value of equity | B35: =Comparables!E9 -> 22867.536 | D35: WACC | E35: 0.0529
A36: Total | B36: =B34+B35 -> 29106.024
D37: Terminal value | E37: =K24*(1+E34)/(E35-E34) -> 287875.84
A38: WACC | B38: =(B28*B32)+(B29*B31) -> 5.3080092 | D38: PV of FCFs | E38: =NPV(E35,G24:K24) -> 13601.075
D39: PV of TV | E39: =E38/(1+E35)^5 -> 10510.844
D40: Enterprise value | E40: =E38+E39 -> 24111.919

Sheet Football Field
C4: low | D4: mid | E4: high
B5: comps using rev x | C5: =Comparables!K13 -> 180.2655 | D5: =Comparables!K14 -> 345.526 | E5: =Comparables!K15 -> 549.42554
B6: comps using EBITx | C6: =Comparables!K19 -> 87.788763 | D6: =Comparables!K20 -> 147.85368 | E6: =Comparables!K15 -> 549.42554
B8: precedent transactions using Revx | C8: ='Precedent Analysis '!G11 -> 42.715625 | D8: ='Precedent Analysis '!G12 -> 311.02149 | E8: ='Precedent Analysis '!G13 -> 838.71714
B10: DCF | C10: =DCF_baseline!H37 -> 85.81 | D10: =DCF_baseline!H38 -> 84.595324 | E10: =DCF_baseline!H39 -> 86.886466
